escape_room/.DS_Store
escape_room/__init__.py
escape_room/__version__.py
escape_room/auth.py
escape_room/config.schema
escape_room/db.py
escape_room/notes.py
escape_room/puzzle.py
escape_room/reader.py
escape_room/room.py
escape_room/schema.sql
escape_room/campaigns/game.json
escape_room/static/.DS_Store
escape_room/static/images/logo.png
escape_room/static/puzzle_images/sunset.jpg
escape_room/static/puzzle_images/volcano.jpg
escape_room/static/puzzle_images/waves.jpg
escape_room/templates/.DS_Store
escape_room/templates/base.html
escape_room/templates/auth/login.html
escape_room/templates/auth/register.html
escape_room/templates/notes/create.html
escape_room/templates/notes/index.html
escape_room/templates/notes/update.html
escape_room/templates/puzzle/index.html
escape_room/templates/puzzle/puzzle.html
escape_room/templates/puzzle/winner.html
virtual_escape_room-0.0.1.dist-info/WHEEL
virtual_escape_room-0.0.1.dist-info/METADATA
virtual_escape_room-0.0.1.dist-info/RECORD
